mends/__init__.py
mends/py.typed
mends-0.1.0.dist-info/LICENSE
mends-0.1.0.dist-info/METADATA
mends-0.1.0.dist-info/WHEEL
mends-0.1.0.dist-info/top_level.txt
mends-0.1.0.dist-info/RECORD
